odoo/addons/crm_autoassign/README.rst
odoo/addons/crm_autoassign/__init__.py
odoo/addons/crm_autoassign/__manifest__.py
odoo/addons/crm_autoassign/post_install.py
odoo/addons/crm_autoassign/data/cron.xml
odoo/addons/crm_autoassign/i18n/es.po
odoo/addons/crm_autoassign/models/__init__.py
odoo/addons/crm_autoassign/models/crm_lead.py
odoo/addons/crm_autoassign/models/crm_stage.py
odoo/addons/crm_autoassign/models/crm_team.py
odoo/addons/crm_autoassign/models/crm_team_member.py
odoo/addons/crm_autoassign/static/description/icon.png
odoo/addons/crm_autoassign/tests/__init__.py
odoo/addons/crm_autoassign/tests/test_crm_atoassign.py
odoo/addons/crm_autoassign/views/crm_stage_views.xml
odoo/addons/crm_autoassign/views/crm_team_member_views.xml
odoo/addons/crm_autoassign/views/crm_team_views.xml
odoo_addon_crm_autoassign-15.0.1.1.0.dist-info/METADATA
odoo_addon_crm_autoassign-15.0.1.1.0.dist-info/WHEEL
odoo_addon_crm_autoassign-15.0.1.1.0.dist-info/top_level.txt
odoo_addon_crm_autoassign-15.0.1.1.0.dist-info/RECORD
